{
  "applications": "*",
  "changelogDate": "20230813141519",
  "clientRootFolder": "hrps-hr",
  "databaseType": "mongodb",
  "dto": "mapstruct",
  "entityTableName": "work_history",
  "fields": [
    {
      "fieldName": "id",
      "fieldType": "Long"
    },
    {
      "fieldName": "employer",
      "fieldType": "String"
    },
    {
      "fieldName": "country",
      "fieldType": "String"
    },
    {
      "fieldName": "state",
      "fieldType": "String"
    },
    {
      "fieldName": "location",
      "fieldType": "String"
    },
    {
      "fieldName": "jobTitle",
      "fieldType": "String"
    },
    {
      "fieldName": "startDate",
      "fieldType": "LocalDate"
    },
    {
      "fieldName": "endDate",
      "fieldType": "LocalDate"
    }
  ],
  "microserviceName": "hrps-hr",
  "name": "WorkHistory",
  "pagination": "pagination",
  "relationships": [
    {
      "otherEntityName": "employee",
      "otherEntityRelationshipName": "workHistory",
      "relationshipName": "employee",
      "relationshipSide": "right",
      "relationshipType": "many-to-one"
    }
  ],
  "searchEngine": "no",
  "service": "serviceImpl"
}
